ComPyTool/DbManager.py
ComPyTool/ExtractFromBam.py
ComPyTool/ExtractFromVCF.py
ComPyTool/MainCompare.py
ComPyTool/MainDelete.py
ComPyTool/MainExtract.py
ComPyTool/MainMerge.py
ComPyTool/MainPlot.py
ComPyTool/PlotAll.py
ComPyTool/PlotData.py
ComPyTool/Preparation.py
ComPyTool/WriteCSV.py
ComPyTool/__init__.py
ComPyTool/__main__.py
ComPyTool/venn.py
ComPyTool-0.2.5.dist-info/LICENSE.txt
ComPyTool-0.2.5.dist-info/METADATA
ComPyTool-0.2.5.dist-info/WHEEL
ComPyTool-0.2.5.dist-info/entry_points.txt
ComPyTool-0.2.5.dist-info/top_level.txt
ComPyTool-0.2.5.dist-info/RECORD
